pyschedule/__init__.py
pyschedule/pyschedule.py
pyschedule/plotters/__init__.py
pyschedule/plotters/matplotlib.py
pyschedule/solvers/__init__.py
pyschedule/solvers/cpoptimizer.py
pyschedule/solvers/docloud.py
pyschedule/solvers/listsched.py
pyschedule/solvers/mip.py
pyschedule/solvers/mip_bigm.py
pyschedule/solvers/mip_pulp.py
pyschedule/solvers/ortools.py
pyschedule/solvers/pulp_scip.py
pyschedule-0.2.33.dist-info/METADATA
pyschedule-0.2.33.dist-info/RECORD
pyschedule-0.2.33.dist-info/WHEEL
pyschedule-0.2.33.dist-info/top_level.txt
