Metadata-Version: 2.1
Name: pyschedule
Version: 0.2.33
Summary: A python package to formulate and solve resource-constrained scheduling problems
Home-page: https://github.com/timnon/pyschedule
Author: Tim Nonner
Author-email: tim@nonner.de
License: Apache 2.0
Platform: UNKNOWN
Requires-Dist: pulp
